docs/source/conf.py
sispca/__init__.py
sispca/data.py
sispca/hcv_vi.py
sispca/model.py
sispca/utils.py
sispca-1.1.0.dist-info/LICENSE
sispca-1.1.0.dist-info/METADATA
sispca-1.1.0.dist-info/WHEEL
sispca-1.1.0.dist-info/top_level.txt
sispca-1.1.0.dist-info/RECORD
