Metadata-Version: 2.2
Name: sispca
Version: 1.1.0
Summary: Supervised independent subspace principal component analysis
Author: Jiayu Su
License: MIT License
Project-URL: repository, https://github.com/JiayuSuPKU/sispca
Requires-Python: <=3.11,>=3.10
License-File: LICENSE
Requires-Dist: torch
Requires-Dist: lightning
Requires-Dist: scipy
Requires-Dist: scikit-learn
